nonlinear_benchmarks/__init__.py
nonlinear_benchmarks/benchmarks.py
nonlinear_benchmarks/error_metrics.py
nonlinear_benchmarks/not_splitted_benchmarks.py
nonlinear_benchmarks/utilities.py
nonlinear_benchmarks-1.0.1.dist-info/licenses/LICENSE
nonlinear_benchmarks-1.0.1.dist-info/METADATA
nonlinear_benchmarks-1.0.1.dist-info/WHEEL
nonlinear_benchmarks-1.0.1.dist-info/RECORD
