Metadata-Version: 2.4
Name: nonlinear_benchmarks
Version: 1.0.1
Summary: The official dataload for http://www.nonlinearbenchmark.org/
License: BSD 3-Clause License
License-File: LICENSE
Author: Gerben I. Beintema
Classifier: License :: Other/Proprietary License
Classifier: Programming Language :: Python :: 2
Classifier: Programming Language :: Python :: 2.7
Classifier: Programming Language :: Python :: 3
Classifier: Programming Language :: Python :: 3.4
Classifier: Programming Language :: Python :: 3.5
Classifier: Programming Language :: Python :: 3.6
Classifier: Programming Language :: Python :: 3.7
Classifier: Programming Language :: Python :: 3.8
Classifier: Programming Language :: Python :: 3.9
Classifier: Programming Language :: Python :: 3.10
Classifier: Programming Language :: Python :: 3.11
Classifier: Programming Language :: Python :: 3.12
Classifier: Programming Language :: Python :: 3.13
Classifier: Programming Language :: Python :: 3.14
Requires-Dist: numpy
Requires-Dist: progressbar
Requires-Dist: rarfile
Requires-Dist: requests
Requires-Dist: scipy
Requires-Dist: tqdm
